git_repo_walker/__init__.py
git_repo_walker/hooks.py
git_repo_walker/walker.py
git_repo_walker-0.1.1.dist-info/entry_points.txt
git_repo_walker-0.1.1.dist-info/WHEEL
git_repo_walker-0.1.1.dist-info/METADATA
git_repo_walker-0.1.1.dist-info/RECORD
