Metadata-Version: 2.1
Name: git-repo-walker
Version: 0.1.1
Summary: 
Author: Daniel Elsner
Author-email: daniel.elsner@tum.de
Requires-Python: >=3.7,<4.0
Classifier: Programming Language :: Python :: 3
Classifier: Programming Language :: Python :: 3.7
Classifier: Programming Language :: Python :: 3.8
Requires-Dist: gitpython (>=3.1.2,<4.0.0)
Requires-Dist: matplotlib (>=3.2.1,<4.0.0)
Requires-Dist: pandas (>=1.0.3,<2.0.0)
